[{"Name":"Susan Nero","thumbnail":" https://static.spankbang.com/pornstarimg/f/7176-250.jpg","numberofVideos":" 39","views":" 212,040","href":"/5jc/pornstar/susan+nero/"},{"Name":"Sol Sanchez","thumbnail":" https://static.spankbang.com/pornstarimg/f/9852-250.jpg","numberofVideos":" 9","views":" 212,000","href":"/7lo/pornstar/sol+sanchez/"},{"Name":"Cory Everson","thumbnail":" https://static.spankbang.com/pornstarimg/f/4224-250.jpg","numberofVideos":" 44","views":" 211,888","href":"/39c/pornstar/cory+everson/"},{"Name":"Ana Marco","thumbnail":" https://static.spankbang.com/pornstarimg/f/1108-250.jpg","numberofVideos":" 19","views":" 211,632","href":"/us/pornstar/ana+marco/"},{"Name":"Suzie Carina","thumbnail":" https://static.spankbang.com/pornstarimg/f/2263-250.jpg","numberofVideos":" 102","views":" 211,407","href":"/1qv/pornstar/suzie+carina/"},{"Name":"Katie Ray","thumbnail":" https://static.spankbang.com/pornstarimg/f/6160-250.jpg","numberofVideos":" 22","views":" 211,392","href":"/4r4/pornstar/katie+ray/"},{"Name":"Ashli Ames","thumbnail":" https://static.spankbang.com/pornstarimg/f/7853-250.jpg","numberofVideos":" 30","views":" 211,356","href":"/625/pornstar/ashli+ames/"},{"Name":"Lady Mai","thumbnail":" https://static.spankbang.com/pornstarimg/f/4260-250.jpg","numberofVideos":" 46","views":" 211,152","href":"/3ac/pornstar/lady+mai/"},{"Name":"Brooke Summers","thumbnail":" https://static.spankbang.com/pornstarimg/f/4219-250.jpg","numberofVideos":" 52","views":" 211,067","href":"/397/pornstar/brooke+summers/"},{"Name":"Emma Luvgood","thumbnail":" https://static.spankbang.com/pornstarimg/f/6923-250.jpg","numberofVideos":" 23","views":" 210,781","href":"/5cb/pornstar/emma+luvgood/"},{"Name":"Audrey Holiday","thumbnail":" https://static.spankbang.com/pornstarimg/f/8366-250.jpg","numberofVideos":" 18","views":" 210,732","href":"/6ge/pornstar/audrey+holiday/"},{"Name":"Emma Redd","thumbnail":" https://static.spankbang.com/pornstarimg/f/6158-250.jpg","numberofVideos":" 15","views":" 210,659","href":"/4r2/pornstar/emma+redd/"},{"Name":"Amber Dawn","thumbnail":" https://static.spankbang.com/pornstarimg/f/7537-250.jpg","numberofVideos":" 10","views":" 210,658","href":"/5td/pornstar/amber+dawn/"},{"Name":"Francesca Felucci","thumbnail":" https://static.spankbang.com/pornstarimg/f/3717-250.jpg","numberofVideos":" 48","views":" 210,583","href":"/2v9/pornstar/francesca+felucci/"},{"Name":"Aileen Ghettman","thumbnail":" https://static.spankbang.com/pornstarimg/f/3888-250.jpg","numberofVideos":" 11","views":" 210,294","href":"/300/pornstar/aileen+ghettman/"},{"Name":"Barbi Sinclair","thumbnail":" https://static.spankbang.com/pornstarimg/f/1288-250.jpg","numberofVideos":" 10","views":" 210,126","href":"/zs/pornstar/barbi+sinclair/"},{"Name":"Zoey Bennett","thumbnail":" https://static.spankbang.com/pornstarimg/f/5002-250.jpg","numberofVideos":" 10","views":" 209,956","href":"/3uy/pornstar/zoey+bennett/"},{"Name":"Sheena Rose","thumbnail":" https://static.spankbang.com/pornstarimg/f/4289-250.jpg","numberofVideos":" 39","views":" 209,951","href":"/3b5/pornstar/sheena+rose/"},{"Name":"Tara Blows","thumbnail":" https://static.spankbang.com/pornstarimg/f/6353-250.jpg","numberofVideos":" 8","views":" 209,805","href":"/4wh/pornstar/tara+blows/"},{"Name":"Suzy Fox","thumbnail":" https://static.spankbang.com/pornstarimg/f/470-250.jpg","numberofVideos":" 7","views":" 209,682","href":"/d2/pornstar/suzy+fox/"},{"Name":"Alejandra","thumbnail":" https://static.spankbang.com/pornstarimg/f/0.jpg","numberofVideos":" 24","views":" 209,357","href":"/61g/pornstar/alejandra/"},{"Name":"Leili Koshi","thumbnail":" https://static.spankbang.com/pornstarimg/f/5318-250.jpg","numberofVideos":" 23","views":" 209,214","href":"/43q/pornstar/leili+koshi/"},{"Name":"Rosaline Love","thumbnail":" https://static.spankbang.com/pornstarimg/f/8337-250.jpg","numberofVideos":" 6","views":" 208,991","href":"/6fl/pornstar/rosaline+love/"},{"Name":"Lacy Green","thumbnail":" https://static.spankbang.com/pornstarimg/f/7078-250.jpg","numberofVideos":" 15","views":" 208,976","href":"/5gm/pornstar/lacy+green/"},{"Name":"Tommy Steel","thumbnail":" https://static.spankbang.com/pornstarimg/f/9167-250.jpg","numberofVideos":" 12","views":" 208,823","href":"/72n/pornstar/tommy+steel/"},{"Name":"Victoria Rose","thumbnail":" https://static.spankbang.com/pornstarimg/f/5627-250.jpg","numberofVideos":" 26","views":" 208,701","href":"/4cb/pornstar/victoria+rose/"},{"Name":"Eva Gomez","thumbnail":" https://static.spankbang.com/pornstarimg/f/439-250.jpg","numberofVideos":" 18","views":" 208,443","href":"/c7/pornstar/eva+gomez/"},{"Name":"Taylor Tilden","thumbnail":" https://static.spankbang.com/pornstarimg/f/5163-250.jpg","numberofVideos":" 14","views":" 208,280","href":"/3zf/pornstar/taylor+tilden/"},{"Name":"Veronica Brazil","thumbnail":" https://static.spankbang.com/pornstarimg/f/2515-250.jpg","numberofVideos":" 49","views":" 208,221","href":"/1xv/pornstar/veronica+brazil/"},{"Name":"Sara Lopez","thumbnail":" https://static.spankbang.com/pornstarimg/f/3059-250.jpg","numberofVideos":" 13","views":" 208,025","href":"/2cz/pornstar/sara+lopez/"},{"Name":"Rylee Peyton","thumbnail":" https://static.spankbang.com/pornstarimg/f/4719-250.jpg","numberofVideos":" 22","views":" 207,940","href":"/3n3/pornstar/rylee+peyton/"},{"Name":"Monica Foster","thumbnail":" https://static.spankbang.com/pornstarimg/f/6075-250.jpg","numberofVideos":" 15","views":" 207,830","href":"/4or/pornstar/monica+foster/"},{"Name":"Sofie Carter","thumbnail":" https://static.spankbang.com/pornstarimg/f/4390-250.jpg","numberofVideos":" 13","views":" 207,686","href":"/3dy/pornstar/sofie+carter/"},{"Name":"Licious Gia","thumbnail":" https://static.spankbang.com/pornstarimg/f/4063-250.jpg","numberofVideos":" 6","views":" 207,521","href":"/34v/pornstar/licious+gia/"},{"Name":"Sophia Bella","thumbnail":" https://static.spankbang.com/pornstarimg/f/4620-250.jpg","numberofVideos":" 31","views":" 207,508","href":"/3kc/pornstar/sophia+bella/"},{"Name":"Emi Sasaki","thumbnail":" https://static.spankbang.com/pornstarimg/f/10059-250.jpg","numberofVideos":" 13","views":" 207,272","href":"/7rf/pornstar/emi+sasaki/"},{"Name":"Pleasure Mia","thumbnail":" https://static.spankbang.com/pornstarimg/f/7351-250.jpg","numberofVideos":" 7","views":" 206,948","href":"/5o7/pornstar/pleasure+mia/"},{"Name":"Lolly Moon","thumbnail":" https://static.spankbang.com/pornstarimg/f/7755-250.jpg","numberofVideos":" 9","views":" 206,532","href":"/5zf/pornstar/lolly+moon/"},{"Name":"Jayla Starr","thumbnail":" https://static.spankbang.com/pornstarimg/f/2762-250.jpg","numberofVideos":" 32","views":" 206,423","href":"/24q/pornstar/jayla+starr/"},{"Name":"Kylie Rose","thumbnail":" https://static.spankbang.com/pornstarimg/f/0.jpg","numberofVideos":" 7","views":" 206,376","href":"/7c8/pornstar/kylie+rose/"},{"Name":"Cris Taliana","thumbnail":" https://static.spankbang.com/pornstarimg/f/4972-250.jpg","numberofVideos":" 27","views":" 206,368","href":"/3u4/pornstar/cris+taliana/"},{"Name":"Sunny McKay","thumbnail":" https://static.spankbang.com/pornstarimg/f/5949-250.jpg","numberofVideos":" 32","views":" 206,239","href":"/4l9/pornstar/sunny+mckay/"},{"Name":"Sara Nice","thumbnail":" https://static.spankbang.com/pornstarimg/f/3583-250.jpg","numberofVideos":" 24","views":" 205,855","href":"/2rj/pornstar/sara+nice/"},{"Name":"Meow 34Jj","thumbnail":" https://static.spankbang.com/pornstarimg/f/6039-250.jpg","numberofVideos":" 53","views":" 205,746","href":"/4nr/pornstar/meow+34jj/"},{"Name":"Elena Nikulina","thumbnail":" https://static.spankbang.com/pornstarimg/f/2947-250.jpg","numberofVideos":" 63","views":" 205,561","href":"/29v/pornstar/elena+nikulina/"},{"Name":"Saskia Steele","thumbnail":" https://static.spankbang.com/pornstarimg/f/3627-250.jpg","numberofVideos":" 22","views":" 205,443","href":"/2sr/pornstar/saskia+steele/"},{"Name":"Kerry Marie","thumbnail":" https://static.spankbang.com/pornstarimg/f/3014-250.jpg","numberofVideos":" 32","views":" 205,136","href":"/2bq/pornstar/kerry+marie/"},{"Name":"Tylene Buck","thumbnail":" https://static.spankbang.com/pornstarimg/f/3586-250.jpg","numberofVideos":" 36","views":" 204,985","href":"/2rm/pornstar/tylene+buck/"},{"Name":"Calli Cox","thumbnail":" https://static.spankbang.com/pornstarimg/f/3915-250.jpg","numberofVideos":" 38","views":" 204,841","href":"/30r/pornstar/calli+cox/"},{"Name":"Taylor Ann","thumbnail":" https://static.spankbang.com/pornstarimg/f/6069-250.jpg","numberofVideos":" 16","views":" 204,818","href":"/4ol/pornstar/taylor+ann/"},{"Name":"Meisa Hanai","thumbnail":" https://static.spankbang.com/pornstarimg/f/2983-250.jpg","numberofVideos":" 13","views":" 204,793","href":"/2av/pornstar/meisa+hanai/"},{"Name":"Angela Crystal","thumbnail":" https://static.spankbang.com/pornstarimg/f/5439-250.jpg","numberofVideos":" 45","views":" 204,624","href":"/473/pornstar/angela+crystal/"},{"Name":"Giselle Humes","thumbnail":" https://static.spankbang.com/pornstarimg/f/5340-250.jpg","numberofVideos":" 9","views":" 204,497","href":"/44c/pornstar/giselle+humes/"},{"Name":"Bianca Mello","thumbnail":" https://static.spankbang.com/pornstarimg/f/2675-250.jpg","numberofVideos":" 8","views":" 204,162","href":"/22b/pornstar/bianca+mello/"},{"Name":"Ayaka Fujikita","thumbnail":" https://static.spankbang.com/pornstarimg/f/5856-250.jpg","numberofVideos":" 8","views":" 204,022","href":"/4io/pornstar/ayaka+fujikita/"},{"Name":"Dunia Montenegro","thumbnail":" https://static.spankbang.com/pornstarimg/f/1279-250.jpg","numberofVideos":" 28","views":" 203,948","href":"/zj/pornstar/dunia+montenegro/"},{"Name":"Laura Love","thumbnail":" https://static.spankbang.com/pornstarimg/f/4821-250.jpg","numberofVideos":" 12","views":" 203,729","href":"/3px/pornstar/laura+love/"},{"Name":"Candy Cotton","thumbnail":" https://static.spankbang.com/pornstarimg/f/4803-250.jpg","numberofVideos":" 42","views":" 203,501","href":"/3pf/pornstar/candy+cotton/"},{"Name":"Veronica Da Souza","thumbnail":" https://static.spankbang.com/pornstarimg/f/947-250.jpg","numberofVideos":" 46","views":" 203,370","href":"/qb/pornstar/veronica+da+souza/"},{"Name":"Kitty Bella","thumbnail":" https://static.spankbang.com/pornstarimg/f/3416-250.jpg","numberofVideos":" 22","views":" 203,216","href":"/2mw/pornstar/kitty+bella/"}]