[{"thumbnailArray":"https://tb.sb-cd.com/t/6249179/6/2/w:800/t6-enh/indian-first-time-fuck.jpg","TitleArray":"Indian first time fuck","durationArray":"12m","likedPercentArray":"90%","viewsArray":" ","previewVideoArray":"https://tbv.sb-cd.com/t/6249179/6/2/td.mp4","hrefArray":"https://spankbang.com/3pxwb/video/indian+first+time+fuck"},{"thumbnailArray":"https://tb.sb-cd.com/t/8856133/8/8/w:800/t6-enh/indian-desi-girl-sex-with-her.jpg","TitleArray":"Indian desi girl sex with her step brother 09593584099","durationArray":"4m","likedPercentArray":"79%","viewsArray":" ","previewVideoArray":"https://tbv.sb-cd.com/t/8856133/8/8/td.mp4","hrefArray":"https://spankbang.com/59tfp/video/indian+desi+girl+sex+with+her+step+brother+09593584099"},{"thumbnailArray":"https://tb.sb-cd.com/t/7322718/7/3/w:800/t6-enh/indian-dance.jpg","TitleArray":"Indian Dance","durationArray":"4m","likedPercentArray":"83%","viewsArray":" ","previewVideoArray":"https://tbv.sb-cd.com/t/7322718/7/3/td.mp4","hrefArray":"https://spankbang.com/4cy8u/video/indian+dance"},{"thumbnailArray":"https://tb.sb-cd.com/t/4062820/4/0/w:800/t2-enh/hot-indian-queen.jpg","TitleArray":"Hot Indian Queen","durationArray":"4m","likedPercentArray":"82%","viewsArray":" ","hrefArray":"https://spankbang.com/2f2w4/video/hot+indian+queen"},{"thumbnailArray":"https://tb.sb-cd.com/t/4833404/4/8/w:800/t1-enh/gorgeous-indian-milf-girl-show.jpg","TitleArray":"Gorgeous Indian milf girl shows his bare feet straight into the camera lens","durationArray":"5m","likedPercentArray":"82%","viewsArray":" ","previewVideoArray":"https://tbv.sb-cd.com/t/4833404/4/8/td.mp4","hrefArray":"https://spankbang.com/2vlh8/video/gorgeous+indian+milf+girl+shows+his+bare+feet+straight+into+the+camera+lens"},{"thumbnailArray":"https://tb.sb-cd.com/t/5680103/5/6/w:800/t6-enh/beautiful-indian-girl.jpg","TitleArray":"Beautiful Indian girl","durationArray":"3m","likedPercentArray":"75%","viewsArray":" ","previewVideoArray":"https://tbv.sb-cd.com/t/5680103/5/6/td.mp4","hrefArray":"https://spankbang.com/3dqsn/video/beautiful+indian+girl"},{"thumbnailArray":"https://tb.sb-cd.com/t/5309558/5/3/w:800/t1-enh/sex-with-indian-in-vacation-on.jpg","TitleArray":"Sex with Indian in VACATION on USA - I met her on SXTINDER.COM","durationArray":"11m","likedPercentArray":"83%","viewsArray":" ","previewVideoArray":"https://tbv.sb-cd.com/t/5309558/5/3/td.mp4","hrefArray":"https://spankbang.com/35svq/video/sex+with+indian+in+vacation+on+usa+i+met+her+on+sxtinder+com"},{"thumbnailArray":"https://tb.sb-cd.com/t/4385513/4/3/w:800/t6-enh/beautiful-indian-posing.jpg","TitleArray":"Beautiful Indian Posing","durationArray":"8m","likedPercentArray":"90%","viewsArray":" ","previewVideoArray":"https://tbv.sb-cd.com/t/4385513/4/3/td.mp4","hrefArray":"https://spankbang.com/2lzvt/video/beautiful+indian+posing"},{"thumbnailArray":"https://tb.sb-cd.com/t/8667446/8/6/w:800/t6-enh/indian-nasty-girl-hardcore-fuc.jpg","TitleArray":"Indian nasty girl hardcore fucked with neighbour 07407850259","durationArray":"5m","likedPercentArray":"90%","viewsArray":" ","previewVideoArray":"https://tbv.sb-cd.com/t/8667446/8/6/td.mp4","hrefArray":"https://spankbang.com/55rue/video/indian+nasty+girl+hardcore+fucked+with+neighbour+07407850259"},{"thumbnailArray":"https://tb.sb-cd.com/t/8908259/8/9/w:800/t6-enh/indian-desi-girl-sex-with-nri.jpg","TitleArray":"Indian desi girl sex with NRI 07479209912","durationArray":"4m","likedPercentArray":"100%","viewsArray":" ","previewVideoArray":"https://tbv.sb-cd.com/t/8908259/8/9/td.mp4","hrefArray":"https://spankbang.com/5axnn/video/indian+desi+girl+sex+with+nri+07479209912"},{"thumbnailArray":"https://tb.sb-cd.com/t/8652583/8/6/w:800/t6-enh/indian-busty-bhabhi-secretly-s.jpg","TitleArray":"Indian busty Bhabhi secretly sex with devar in bathroom 08001461038","durationArray":"5m","likedPercentArray":"100%","viewsArray":" ","previewVideoArray":"https://tbv.sb-cd.com/t/8652583/8/6/td.mp4","hrefArray":"https://spankbang.com/55gdj/video/indian+busty+bhabhi+secretly+sex+with+devar+in+bathroom+08001461038"},{"thumbnailArray":"https://tb.sb-cd.com/t/4393142/4/3/w:800/t1-enh/indian-suck-off.jpg","TitleArray":"Indian Suck off","durationArray":"7m","likedPercentArray":"93%","viewsArray":" ","previewVideoArray":"https://tbv.sb-cd.com/t/4393142/4/3/td.mp4","hrefArray":"https://spankbang.com/2m5rq/video/indian+suck+off"},{"thumbnailArray":"https://tb.sb-cd.com/t/7139110/7/1/w:800/t8-enh/indian-queen-bbd-intro.jpg","TitleArray":"indian_queen_-_bbd_intro","durationArray":"7m","likedPercentArray":"96%","viewsArray":" ","previewVideoArray":"https://tbv.sb-cd.com/t/7139110/7/1/td.mp4","hrefArray":"https://spankbang.com/490km/video/indian+queen+bbd+intro"},{"thumbnailArray":"https://tb.sb-cd.com/t/5240364/5/2/w:800/t10-enh/indian-slut-public-bathroom-bl.jpg","TitleArray":"Indian Slut Public Bathroom Blowjob","durationArray":"5m","likedPercentArray":"77%","viewsArray":" ","previewVideoArray":"https://tbv.sb-cd.com/t/5240364/5/2/td.mp4","hrefArray":"https://spankbang.com/34bho/video/indian+slut+public+bathroom+blowjob"},{"thumbnailArray":"https://tb.sb-cd.com/t/9485649/9/4/w:800/t6-enh/indian-milf.jpg","TitleArray":"indian milf","durationArray":"10m","likedPercentArray":"79%","viewsArray":" ","previewVideoArray":"https://tbv.sb-cd.com/t/9485649/9/4/td.mp4","hrefArray":"https://spankbang.com/5nb69/video/indian+milf"},{"thumbnailArray":"https://tb.sb-cd.com/t/7999347/7/9/w:800/t6-enh/white-girl-in-indian-attire-gi.jpg","TitleArray":"White Girl in Indian Attire Gives Sensual Whipped Cream Blowjob","durationArray":"10m","likedPercentArray":"74%","viewsArray":" ","previewVideoArray":"https://tbv.sb-cd.com/t/7999347/7/9/td.mp4","hrefArray":"https://spankbang.com/4rgc3/video/white+girl+in+indian+attire+gives+sensual+whipped+cream+blowjob"},{"thumbnailArray":"https://tb.sb-cd.com/t/9243934/9/2/w:800/t6-enh/big-tits-indian-succk-his-hous.jpg","TitleArray":"big tits indian succk his housband","durationArray":"10m","likedPercentArray":"74%","viewsArray":" ","previewVideoArray":"https://tbv.sb-cd.com/t/9243934/9/2/td.mp4","hrefArray":"https://spankbang.com/5i4ny/video/big+tits+indian+succk+his+housband"},{"thumbnailArray":"https://tb.sb-cd.com/t/8356044/8/3/w:800/t6-enh/new-indian-pussy-fucking-when.jpg","TitleArray":"New Indian Pussy Fucking When Bhabhi Alone at Night","durationArray":"10m","likedPercentArray":"78%","viewsArray":" ","previewVideoArray":"https://tbv.sb-cd.com/t/8356044/8/3/td.mp4","hrefArray":"https://spankbang.com/4z3kc/video/new+indian+pussy+fucking+when+bhabhi+alone+at+night"},{"thumbnailArray":"https://tb.sb-cd.com/t/10974342/1/0/w:800/t6-enh/imaf-indian-bull-cuckold-asian.jpg","TitleArray":"IMAF Indian bull cuckold asian wife 7","durationArray":"5m","likedPercentArray":"74%","viewsArray":" ","previewVideoArray":"https://tbv.sb-cd.com/t/10974342/1/0/td.mp4","hrefArray":"https://spankbang.com/6j7uu/video/imaf+indian+bull+cuckold+asian+wife+7"},{"thumbnailArray":"https://tb.sb-cd.com/t/6969247/6/9/w:800/t6-enh/hot-indian.jpg","TitleArray":"hot indian","durationArray":"13m","likedPercentArray":"82%","viewsArray":" ","previewVideoArray":"https://tbv.sb-cd.com/t/6969247/6/9/td.mp4","hrefArray":"https://spankbang.com/45di7/video/hot+indian"},{"thumbnailArray":"https://tb.sb-cd.com/t/7808746/7/8/w:800/t6-enh/indian-web-series.jpg","TitleArray":"indian web series","durationArray":"2m","likedPercentArray":"77%","viewsArray":" ","previewVideoArray":"https://tbv.sb-cd.com/t/7808746/7/8/td.mp4","hrefArray":"https://spankbang.com/4nd9m/video/indian+web+series"},{"thumbnailArray":"https://tb.sb-cd.com/t/3029117/3/0/w:800/t6-enh/fat-indian-girl-deepali-fucked.jpg","TitleArray":"fat indian girl deepali fucked hard sex by her boyfriend new indian sex video","durationArray":"2m","likedPercentArray":"76%","viewsArray":" ","hrefArray":"https://spankbang.com/1sxa5/video/fat+indian+girl+deepali+fucked+hard+sex+by+her+boyfriend+new+indian+sex+video"},{"thumbnailArray":"https://tb.sb-cd.com/t/3037451/3/0/w:800/t6-enh/big-tit-indian-gets-pounded-by.jpg","TitleArray":"big tit indian gets pounded by 2 guys","durationArray":"12m","likedPercentArray":"97%","viewsArray":" ","previewVideoArray":"https://tbv.sb-cd.com/t/3037451/3/0/td.mp4","hrefArray":"https://spankbang.com/1t3pn/video/big+tit+indian+gets+pounded+by+2+guys"},{"thumbnailArray":"https://tb.sb-cd.com/t/3363264/3/3/w:800/t6-enh/indian-wifes-creampied.jpg","TitleArray":"Indian Wifes Creampied","durationArray":"10m","likedPercentArray":"91%","viewsArray":" ","previewVideoArray":"https://tbv.sb-cd.com/t/3363264/3/3/td.mp4","hrefArray":"https://spankbang.com/20340/video/indian+wifes+creampied"},{"thumbnailArray":"https://tb.sb-cd.com/t/4494565/4/4/w:800/t6-enh/indian.jpg","TitleArray":"indian","durationArray":"8m","likedPercentArray":"85%","viewsArray":" ","previewVideoArray":"https://tbv.sb-cd.com/t/4494565/4/4/td.mp4","hrefArray":"https://spankbang.com/2oc11/video/indian"},{"thumbnailArray":"https://tb.sb-cd.com/t/3292375/3/2/w:800/t10-enh/indian-slut-sucks-two-cocks-pa.jpg","TitleArray":"Indian slut sucks two cocks-part2 on webgirlsoncam.com","durationArray":"5m","likedPercentArray":"76%","viewsArray":" ","hrefArray":"https://spankbang.com/1ykev/video/indian+slut+sucks+two+cocks+part2+on+webgirlsoncam+com"},{"thumbnailArray":"https://tb.sb-cd.com/t/1526681/1/5/w:800/t6-enh/indian-home-made.jpg","TitleArray":"indian home made","durationArray":"5m","likedPercentArray":"77%","viewsArray":" ","previewVideoArray":"https://tbv.sb-cd.com/t/1526681/1/5/td.mp4","hrefArray":"https://spankbang.com/wpzt/video/indian+home+made"},{"thumbnailArray":"https://tb.sb-cd.com/t/537951/5/3/w:800/t6-enh/busty-and-voluptuous-indian-gi.jpg","TitleArray":"Busty and Voluptuous Indian Girl","durationArray":"4m","likedPercentArray":"86%","viewsArray":" ","hrefArray":"https://spankbang.com/bj33/video/busty+and+voluptuous+indian+girl"},{"thumbnailArray":"https://tb.sb-cd.com/t/371563/3/7/w:800/t6-enh/indian-gf-bj-licks-balls-and-n.jpg","TitleArray":"Indian gf bj licks balls and nice dick best blowjob","durationArray":"5m","likedPercentArray":"74%","viewsArray":" ","hrefArray":"https://spankbang.com/7yp7/video/indian+gf+bj+licks+balls+and+nice+dick+best+blowjob"},{"thumbnailArray":"https://tb.sb-cd.com/t/2475687/2/4/w:800/t6-enh/indian.jpg","TitleArray":"Indian","durationArray":"3m","likedPercentArray":"72%","viewsArray":" ","hrefArray":"https://spankbang.com/1h293/video/indian"},{"thumbnailArray":"https://tb.sb-cd.com/t/235127/2/3/w:800/t6-enh/nude-indian-babe-pleases.jpg","TitleArray":"Nude indian babe pleases","durationArray":"6m","likedPercentArray":"74%","viewsArray":" ","hrefArray":"https://spankbang.com/51fb/video/nude+indian+babe+pleases"},{"thumbnailArray":"https://tb.sb-cd.com/t/1219864/1/2/w:800/t1-enh/indian-girlfriend-fingers-hers.jpg","TitleArray":"indian girlfriend fingers herself on cam","durationArray":"5m","likedPercentArray":"82%","viewsArray":" ","previewVideoArray":"https://tbv.sb-cd.com/t/1219864/1/2/td.mp4","hrefArray":"https://spankbang.com/q594/video/indian+girlfriend+fingers+herself+on+cam"},{"thumbnailArray":"https://tb.sb-cd.com/t/3524870/3/5/w:800/t3-enh/sweet-indian-fingered-and-fuck.jpg","TitleArray":"Sweet Indian fingered and fucked","durationArray":"13m","likedPercentArray":"90%","viewsArray":" ","previewVideoArray":"https://tbv.sb-cd.com/t/3524870/3/5/td.mp4","hrefArray":"https://spankbang.com/23jt2/video/sweet+indian+fingered+and+fucked"},{"thumbnailArray":"https://tb.sb-cd.com/t/2237869/2/2/w:800/t6-enh/indian.jpg","TitleArray":"indian","durationArray":"5m","likedPercentArray":"79%","viewsArray":" ","previewVideoArray":"https://tbv.sb-cd.com/t/2237869/2/2/td.mp4","hrefArray":"https://spankbang.com/1byr1/video/indian"}]